myjlab/__init__.py
myjlab/pbl/__init__.py
myjlab/pbl/utils.py
myjlab-0.0.1.dist-info/METADATA
myjlab-0.0.1.dist-info/WHEEL
myjlab-0.0.1.dist-info/licenses/LICENSE
myjlab-0.0.1.dist-info/RECORD
